cmf/__init__.py
cmf/_cmf_core.cp311-win_amd64.pdb
cmf/_cmf_core.cp311-win_amd64.pyd
cmf/cmf_core.py
cmf/convert_1_to_2.py
cmf/describe.py
cmf/fit_retention_curve.py
cmf/jacobian.py
cmf/maps.py
cmf/timetools.py
cmf/draw/__init__.py
cmf/draw/cellmap.py
cmf/draw/draw_misc.py
cmf/draw/hillplot.py
cmf/draw/shapemap.py
cmf/geometry/__init__.py
cmf/geometry/geocell.py
cmf/geometry/irregular_grid.py
cmf/geometry/qtree.py
cmf-2.0.1.dist-info/METADATA
cmf-2.0.1.dist-info/WHEEL
cmf-2.0.1.dist-info/license.txt
cmf-2.0.1.dist-info/top_level.txt
cmf-2.0.1.dist-info/RECORD
