Metadata-Version: 2.1
Name: cmf
Version: 2.0.1
Summary: Catchment Modelling Framework - A hydrological modelling toolkit
Home-page: https://www.uni-giessen.de/hydro/download
Author: Philipp Kraft
Author-email: philipp.kraft@umwelt.uni-giessen.de
License: GPLv3+
Keywords: hydrology catchment simulation toolbox
Classifier: Development Status :: 4 - Beta
Classifier: Intended Audience :: Science/Research
Classifier: License :: OSI Approved :: GNU General Public License v3 or later (GPLv3+)
Classifier: Programming Language :: C++
Classifier: Programming Language :: Python
Classifier: Programming Language :: Python :: 3.8
Classifier: Programming Language :: Python :: 3.9
Classifier: Programming Language :: Python :: 3.10
Classifier: Programming Language :: Python :: 3.11
Classifier: Topic :: Scientific/Engineering
Classifier: Topic :: Software Development :: Libraries :: Python Modules
Requires-Python: >=3.5
License-File: license.txt
Requires-Dist: numpy>=1.11.1
